{
    "AX": {
        "error": 0.04919435656645969, 
        "fit": "average", 
        "value": -0.07812368013520954
    }, 
    "CDD": {
        "error": 0.00017639129808861296, 
        "fit": "average", 
        "value": 0.00021264034827860693
    }, 
    "H1": {
        "error": 0.09325478210136627, 
        "fit": "average", 
        "value": -0.008936816027894486
    }, 
    "H2": {
        "error": 0.07155942022824249, 
        "fit": "average", 
        "value": -0.010762980124574122
    }, 
    "L1": {
        "error": 0.09518566058492439, 
        "fit": "average", 
        "value": -0.11477810098744079
    }, 
    "L2": {
        "error": 0.11395127913307786, 
        "fit": "average", 
        "value": -0.013061602063224478
    }
}