{
    "AX": {
        "error": 0.050634439362694406, 
        "fit": "average", 
        "value": -0.10002059387173584
    }, 
    "CDD": {
        "error": 0.00017124154965699633, 
        "fit": "average", 
        "value": 0.00023937955362877497
    }, 
    "H1": {
        "error": 0.10061888421821613, 
        "fit": "average", 
        "value": 0.01888403030366728
    }, 
    "H2": {
        "error": 0.10408012814413568, 
        "fit": "average", 
        "value": -0.02894639007879042
    }, 
    "L1": {
        "error": 0.09116231393519736, 
        "fit": "average", 
        "value": -0.08710374582181524
    }, 
    "L2": {
        "error": 0.11861839605417004, 
        "fit": "average", 
        "value": -0.014488468978329208
    }
}